odoo/addons/base_edi/README.rst
odoo/addons/base_edi/__init__.py
odoo/addons/base_edi/__manifest__.py
odoo/addons/base_edi/data/module_category.xml
odoo/addons/base_edi/i18n/base_edi.pot
odoo/addons/base_edi/i18n/fr.po
odoo/addons/base_edi/i18n/nl.po
odoo/addons/base_edi/readme/CONTRIBUTORS.rst
odoo/addons/base_edi/readme/DESCRIPTION.rst
odoo/addons/base_edi/readme/ROADMAP.rst
odoo/addons/base_edi/security/edi_groups.xml
odoo/addons/base_edi/static/description/icon.png
odoo/addons/base_edi/static/description/icon.svg
odoo/addons/base_edi/static/description/index.html
odoo/addons/base_edi/views/edi_menu.xml
odoo14_addon_base_edi-14.0.1.1.0.dist-info/METADATA
odoo14_addon_base_edi-14.0.1.1.0.dist-info/WHEEL
odoo14_addon_base_edi-14.0.1.1.0.dist-info/top_level.txt
odoo14_addon_base_edi-14.0.1.1.0.dist-info/RECORD
